passim/__init__.py
passim/core.py
passim/utils.py
passim-0.1.0.dist-info/METADATA
passim-0.1.0.dist-info/WHEEL
passim-0.1.0.dist-info/top_level.txt
passim-0.1.0.dist-info/RECORD
