Metadata-Version: 2.2
Name: passim
Version: 0.1.0
Summary: A lightweight, secure Python library for checking password similarity
Home-page: https://github.com/nasredeenabdulhaleem/passim
Author: Abdulhaleem Nasredeen
Author-email: Abdulhaleem Nasredeen <nabdulhaleem09@gmail.com>
License: MIT
Project-URL: Homepage, https://github.com/nasredeenabdulhaleem/passim
Project-URL: Bug Tracker, https://github.com/nasredeenabdulhaleem/passim/issues
Classifier: Programming Language :: Python :: 3
Classifier: License :: OSI Approved :: MIT License
Classifier: Operating System :: OS Independent
Requires-Python: >=3.6
Requires-Dist: bcrypt>=4.2.1
Dynamic: author
Dynamic: home-page
Dynamic: requires-python
